needle/__init__.py
needle/pointer/__init__.py
needle/pointer/__init__.stitcher.yaml
needle/pointer/core.py
needle/pointer/core.stitcher.yaml
needle/pointer/set.py
needle/pointer/set.stitcher.yaml
pyneedle_pointer-0.2.1.dist-info/METADATA
pyneedle_pointer-0.2.1.dist-info/WHEEL
pyneedle_pointer-0.2.1.dist-info/RECORD
